{
  "project_info": {
    "project_number": "230384482487",
    "project_id": "building-automation-a802a",
    "storage_bucket": "building-automation-a802a.appspot.com"
  },
  "client": [
    {
      "client_info": {
        "mobilesdk_app_id": "1:230384482487:android:dfee30691e7bc3e280b532",
        "android_client_info": {
          "package_name": "com.srishakthi.automation"
        }
      },
      "oauth_client": [
        {
          "client_id": "230384482487-bmn0q543g6nmel9vnorg764h098g3hv8.apps.googleusercontent.com",
          "client_type": 3
        }
      ],
      "api_key": [
        {
          "current_key": "AIzaSyATY2dkq_4rOEZIXOc0icnJPqtm0-5vOJ0"
        }
      ],
      "services": {
        "appinvite_service": {
          "other_platform_oauth_client": [
            {
              "client_id": "230384482487-bmn0q543g6nmel9vnorg764h098g3hv8.apps.googleusercontent.com",
              "client_type": 3
            }
          ]
        }
      }
    }
  ],
  "configuration_version": "1"
}